aiodirigera/__init__.py
aiodirigera/api.py
aiodirigera/api_model.py
aiodirigera/auth.py
aiodirigera/hub.py
aiodirigera/device/__init__.py
aiodirigera/device/device.py
aiodirigera/device/light.py
aiodirigera/device/sensor.py
aiodirigera-0.0.6.dist-info/LICENSE
aiodirigera-0.0.6.dist-info/METADATA
aiodirigera-0.0.6.dist-info/WHEEL
aiodirigera-0.0.6.dist-info/top_level.txt
aiodirigera-0.0.6.dist-info/RECORD
